walking_man/__init__.py
walking_man/adventure.py
walking_man/walking_man.py
walking_man-0.2.8.dist-info/LICENSE
walking_man-0.2.8.dist-info/METADATA
walking_man-0.2.8.dist-info/WHEEL
walking_man-0.2.8.dist-info/entry_points.txt
walking_man-0.2.8.dist-info/RECORD
