Metadata-Version: 2.3
Name: walking-man
Version: 0.2.8
Summary: A friendly companion while you wait
Author: Danny Stewart
Author-email: danny@stewart.cc
Requires-Python: >=3.12
Classifier: Development Status :: 5 - Production/Stable
Classifier: Intended Audience :: Developers
Classifier: License :: OSI Approved :: MIT License
Classifier: Programming Language :: Python :: 3
Classifier: Programming Language :: Python :: 3.12
Classifier: Programming Language :: Python :: 3.13
Classifier: Topic :: Software Development :: Libraries
Classifier: Topic :: Software Development :: Libraries :: Python Modules
Classifier: Topic :: System :: Shells
Classifier: Topic :: System :: System Shells
Classifier: Topic :: Utilities
Requires-Dist: polykit (>=0.1.1)
